debug_toolbar_line_profiler/__init__.py
debug_toolbar_line_profiler/panel.py
debug_toolbar_line_profiler/signals.py
debug_toolbar_line_profiler/templates/debug_toolbar_line_profiler/panels/profiling.html
django_debug_toolbar_line_profiling-0.8.1.dist-info/LICENSE
django_debug_toolbar_line_profiling-0.8.1.dist-info/METADATA
django_debug_toolbar_line_profiling-0.8.1.dist-info/WHEEL
django_debug_toolbar_line_profiling-0.8.1.dist-info/top_level.txt
django_debug_toolbar_line_profiling-0.8.1.dist-info/RECORD
