Metadata-Version: 2.1
Name: django-debug-toolbar-line-profiling
Version: 0.8.1
Summary: A panel for django-debug-toolbar that integrates information from line_profiler
Home-page: https://github.com/mikekeda/django-debug-toolbar-line-profiler
Download-URL: https://pypi.python.org/pypi/django-debug-toolbar-line-profiling
Author: Mykhailo Keda
Author-email: mriynuk@gmail.com
License: BSD
Classifier: Development Status :: 4 - Beta
Classifier: Environment :: Web Environment
Classifier: Framework :: Django
Classifier: Intended Audience :: Developers
Classifier: License :: OSI Approved :: BSD License
Classifier: Operating System :: OS Independent
Classifier: Programming Language :: Python
Classifier: Programming Language :: Python :: 3
Classifier: Programming Language :: Python :: 3 :: Only
Classifier: Programming Language :: Python :: 3.9
Classifier: Programming Language :: Python :: 3.10
Classifier: Programming Language :: Python :: 3.11
Classifier: Programming Language :: Python :: 3.12
Classifier: Topic :: Software Development :: Libraries :: Python Modules
License-File: LICENSE
Requires-Dist: django-debug-toolbar >=4.0.0
Requires-Dist: line-profiler >=3.4.0
